[{"imports": ["Archangel", "Deadpool", "Wolverine", "Warpath", "Banshee (Theresa Rourke)", "Forge", "Sunspot", "Human Torch", "Beast", "Invisible Woman", "X-Force", "Adam Warlock", "Emma Frost", "Banshee", "Thing", "Cyclops", "Iceman", "X-Factor", "Cannonball", "Professor X", "Domino", "Shatterstar"], "name": "X-Men"}, {"imports": ["Wolverine"], "name": "Iron Man"}, {"imports": ["Beast", "Iron Man", "Emma Frost", "Cable", "Colossus", "X-Men", "Cyclops", "Warpath", "Nightcrawler", "Bishop"], "name": "Wolverine"}, {"imports": ["Nick Fury", "Loki", "Odin"], "name": "Thor"}, {"imports": ["Archangel", "Sub-Mariner", "X-Men", "X-Factor", "Sunspot", "Banshee", "Beast", "Thing", "Cyclops", "Cannonball", "Forge", "Invisible Woman", "Adam Warlock", "Iceman"], "name": "Human Torch"}, {"imports": ["Archangel", "Havok", "Wolverine", "Warpath", "Forge", "Sunspot", "Human Torch", "Beast", "Invisible Woman", "Adam Warlock", "Emma Frost", "Cable", "Colossus", "Banshee", "Thing", "Iceman", "X-Factor", "Cannonball", "X-Men", "Professor X", "Nightcrawler", "Bishop"], "name": "Cyclops"}, {"imports": ["Wolverine", "Archangel", "Emma Frost", "Cable", "X-Men", "Colossus", "X-Factor", "Sunspot", "Human Torch", "Banshee", "Thing", "Cyclops", "Cannonball", "Invisible Woman", "Forge", "Warpath", "Nightcrawler", "Bishop", "Adam Warlock", "Iceman"], "name": "Beast"}, {"imports": ["Wolverine", "Emma Frost", "Cable", "Beast", "Cyclops", "Warpath", "Nightcrawler", "Bishop"], "name": "Colossus"}, {"imports": ["Human Torch"], "name": "Sub-Mariner"}, {"imports": ["Sunspot", "Professor X", "X-Factor", "X-Men", "Human Torch", "Banshee", "Beast", "Thing", "Cyclops", "Cannonball", "Forge", "Invisible Woman", "Adam Warlock", "Iceman"], "name": "Archangel"}, {"imports": ["Wolverine", "Emma Frost", "Cable", "Colossus", "Beast", "Cyclops", "Warpath", "Bishop"], "name": "Nightcrawler"}, {"imports": ["Archangel", "X-Men", "X-Factor", "Sunspot", "Human Torch", "Banshee", "Beast", "Cyclops", "Adam Warlock", "Forge", "Invisible Woman", "Cannonball", "Iceman"], "name": "Thing"}, {"imports": ["Archangel", "X-Men", "X-Factor", "Sunspot", "Human Torch", "Banshee", "Beast", "Thing", "Cyclops", "Adam Warlock", "Forge", "Invisible Woman", "Cannonball"], "name": "Iceman"}, {"imports": ["Archangel", "X-Men", "X-Factor", "Sunspot", "Human Torch", "Banshee", "Beast", "Thing", "Cyclops", "Adam Warlock", "Forge", "Cannonball", "Iceman"], "name": "Invisible Woman"}, {"imports": ["X-Men", "Domino", "Shatterstar", "Warpath", "Banshee (Theresa Rourke)", "X-Force", "Cannonball"], "name": "Deadpool"}, {"imports": ["Archangel", "Cyclops", "X-Men"], "name": "Professor X"}, {"imports": ["Wolverine", "Emma Frost", "Colossus", "Beast", "Cyclops", "Warpath", "Nightcrawler", "Bishop"], "name": "Cable"}, {"imports": ["Loki", "Odin", "Thor"], "name": "Nick Fury"}, {"imports": ["Wolverine", "Emma Frost", "Cable", "Colossus", "Beast", "Cyclops", "Warpath", "Nightcrawler"], "name": "Bishop"}, {"imports": ["Shatterstar", "Archangel", "Deadpool", "Warpath", "X-Men", "Domino", "X-Factor", "Sunspot", "Human Torch", "Banshee", "Beast", "Thing", "Cyclops", "Adam Warlock", "Banshee (Theresa Rourke)", "Forge", "Invisible Woman", "X-Force", "Iceman"], "name": "Cannonball"}, {"imports": ["Cyclops"], "name": "Havok"}, {"imports": ["X-Men", "Deadpool", "Domino", "Shatterstar", "Warpath", "Banshee (Theresa Rourke)", "Cannonball"], "name": "X-Force"}, {"imports": ["Wolverine", "X-Men", "Cable", "Colossus", "Beast", "Cyclops", "Warpath", "Nightcrawler", "Bishop"], "name": "Emma Frost"}, {"imports": ["Nick Fury", "Odin", "Thor"], "name": "Loki"}, {"imports": ["Archangel", "X-Men", "X-Factor", "Sunspot", "Human Torch", "Beast", "Thing", "Cyclops", "Adam Warlock", "Forge", "Invisible Woman", "Cannonball", "Iceman"], "name": "Banshee"}, {"imports": ["Wolverine", "X-Men", "Emma Frost", "Cable", "X-Force", "Deadpool", "Colossus", "Shatterstar", "Beast", "Domino", "Cyclops", "Banshee (Theresa Rourke)", "Nightcrawler", "Bishop", "Cannonball"], "name": "Warpath"}, {"imports": ["Archangel", "X-Men", "X-Factor", "Human Torch", "Banshee", "Beast", "Thing", "Cyclops", "Adam Warlock", "Forge", "Invisible Woman", "Cannonball", "Iceman"], "name": "Sunspot"}, {"imports": ["Nick Fury", "Loki", "Thor"], "name": "Odin"}, {"imports": ["X-Men", "Deadpool", "Domino", "Shatterstar", "Warpath", "X-Force", "Cannonball"], "name": "Banshee (Theresa Rourke)"}, {"imports": ["X-Men", "Deadpool", "Shatterstar", "Warpath", "Banshee (Theresa Rourke)", "X-Force", "Cannonball"], "name": "Domino"}, {"imports": ["Archangel", "X-Men", "X-Factor", "Sunspot", "Human Torch", "Banshee", "Beast", "Thing", "Cyclops", "Adam Warlock", "Invisible Woman", "Cannonball", "Iceman"], "name": "Forge"}, {"imports": ["Archangel", "X-Men", "X-Factor", "Sunspot", "Human Torch", "Banshee", "Beast", "Thing", "Cyclops", "Forge", "Invisible Woman", "Cannonball", "Iceman"], "name": "Adam Warlock"}, {"imports": ["Archangel", "X-Men", "Sunspot", "Human Torch", "Banshee", "Beast", "Thing", "Cyclops", "Adam Warlock", "Forge", "Invisible Woman", "Cannonball", "Iceman"], "name": "X-Factor"}, {"imports": ["X-Men", "Deadpool", "Domino", "Warpath", "Banshee (Theresa Rourke)", "X-Force", "Cannonball"], "name": "Shatterstar"}]